pywb/__init__.py
pywb/default_config.yaml
pywb/git_hash.py
pywb/rules.yaml
pywb/version.py
pywb/apps/__init__.py
pywb/apps/cli.py
pywb/apps/frontendapp.py
pywb/apps/live.py
pywb/apps/rewriterapp.py
pywb/apps/static_handler.py
pywb/apps/warcserverapp.py
pywb/apps/wayback.py
pywb/apps/wbrequestresponse.py
pywb/indexer/__init__.py
pywb/indexer/archiveindexer.py
pywb/indexer/cdxindexer.py
pywb/manager/__init__.py
pywb/manager/aclmanager.py
pywb/manager/autoindex.py
pywb/manager/locmanager.py
pywb/manager/manager.py
pywb/manager/migrate.py
pywb/recorder/__init__.py
pywb/recorder/filters.py
pywb/recorder/multifilewarcwriter.py
pywb/recorder/recorderapp.py
pywb/recorder/redisindexer.py
pywb/rewrite/__init__.py
pywb/rewrite/content_rewriter.py
pywb/rewrite/cookie_rewriter.py
pywb/rewrite/cookies.py
pywb/rewrite/default_rewriter.py
pywb/rewrite/header_rewriter.py
pywb/rewrite/html_insert_rewriter.py
pywb/rewrite/html_rewriter.py
pywb/rewrite/jsonp_rewriter.py
pywb/rewrite/regex_rewriters.py
pywb/rewrite/rewrite_amf.py
pywb/rewrite/rewrite_dash.py
pywb/rewrite/rewrite_hls.py
pywb/rewrite/rewrite_js_workers.py
pywb/rewrite/rewriteinputreq.py
pywb/rewrite/templateview.py
pywb/rewrite/url_rewriter.py
pywb/rewrite/wburl.py
pywb/static/autoFetchWorker.js
pywb/static/calendar.svg
pywb/static/loadWabac.js
pywb/static/pywb-logo-sm.png
pywb/static/pywb-logo.png
pywb/static/query.js
pywb/static/queryWorker.js
pywb/static/scroll-webkit.css
pywb/static/search.js
pywb/static/transclusions.js
pywb/static/vidrw.js
pywb/static/vue_banner.css
pywb/static/wabacSW.js
pywb/static/wb_frame.js
pywb/static/wombat.js
pywb/static/wombatProxyMode.js
pywb/static/wombatWorkers.js
pywb/static/css/base.css
pywb/static/css/bootstrap.min.css
pywb/static/css/font-awesome.min.css
pywb/static/css/query.css
pywb/static/flowplayer/flowplayer-3.2.18.swf
pywb/static/flowplayer/flowplayer.audio-3.2.11.swf
pywb/static/flowplayer/flowplayer.controls-3.2.16.swf
pywb-2.9.1.dist-info/LICENSE
pywb-2.9.1.dist-info/METADATA
pywb-2.9.1.dist-info/NOTICE
pywb-2.9.1.dist-info/WHEEL
pywb-2.9.1.dist-info/entry_points.txt
pywb-2.9.1.dist-info/top_level.txt
pywb-2.9.1.dist-info/RECORD
