Metadata-Version: 2.1
Name: pywb
Version: 2.9.1
Summary: Pywb Webrecorder web archive replay and capture tools
Home-page: https://github.com/webrecorder/pywb
Author: Ilya Kreymer
Author-email: ikreymer@gmail.com
License: GPL
Platform: UNKNOWN
Classifier: Development Status :: 4 - Beta
Classifier: Environment :: Web Environment
Classifier: License :: OSI Approved :: GNU General Public License (GPL)
Classifier: License :: OSI Approved :: GNU General Public License v3 (GPLv3)
Classifier: Programming Language :: Python :: 3
Classifier: Programming Language :: Python :: 3.7
Classifier: Programming Language :: Python :: 3.8
Classifier: Programming Language :: Python :: 3.9
Classifier: Programming Language :: Python :: 3.10
Classifier: Programming Language :: Python :: 3.11
Classifier: Programming Language :: Python :: 3.12
Classifier: Topic :: Internet :: Proxy Servers
Classifier: Topic :: Internet :: WWW/HTTP
Classifier: Topic :: Internet :: WWW/HTTP :: WSGI
Classifier: Topic :: Internet :: WWW/HTTP :: WSGI :: Application
Classifier: Topic :: Internet :: WWW/HTTP :: WSGI :: Middleware
Classifier: Topic :: Internet :: WWW/HTTP :: WSGI :: Server
Classifier: Topic :: Software Development :: Libraries :: Python Modules
Classifier: Topic :: System :: Archiving
Classifier: Topic :: System :: Archiving :: Backup
Classifier: Topic :: Utilities
Requires-Python: >=3.7,<3.13
License-File: LICENSE
License-File: NOTICE
Requires-Dist: six
Requires-Dist: warcio>=1.7.1
Requires-Dist: requests
Requires-Dist: redis==2.10.6
Requires-Dist: jinja2>=3.1.2
Requires-Dist: surt>=0.3.1
Requires-Dist: brotlipy
Requires-Dist: pyyaml
Requires-Dist: werkzeug==2.2.3
Requires-Dist: webencodings
Requires-Dist: webassets==2.0
Requires-Dist: portalocker
Requires-Dist: wsgiprox>=1.5.1
Requires-Dist: fakeredis<1.0
Requires-Dist: tldextract
Requires-Dist: python-dateutil
Requires-Dist: markupsafe>=2.1.1
Requires-Dist: ua-parser
Requires-Dist: py3AMF
Requires-Dist: greenlet<3.0,>=2.0.2; python_version < "3.12"
Requires-Dist: gevent==22.10.2; python_version < "3.8"
Requires-Dist: greenlet==3.2.4; python_version >= "3.12.0rc0"
Requires-Dist: gevent==23.9.0.post1; python_version >= "3.8"
Provides-Extra: i18n
Requires-Dist: babel; extra == "i18n"
Requires-Dist: translate-toolkit; extra == "i18n"
